meteorite-0.1.0.dist-info/METADATA
meteorite-0.1.0.dist-info/WHEEL
meteorite-0.1.0.dist-info/license_files/LICENSE
meteorite/__init__.py
meteorite/__init__.pyi
meteorite/py.typed
meteorite/meteorite.cpython-38-darwin.so
meteorite-0.1.0.dist-info/RECORD
