Metadata-Version: 2.1
Name: meteorite
Version: 0.1.0
License-File: LICENSE
Summary: A fast and simple web server for machine learning models
Keywords: model,server,api,hosting
Maintainer-email: Utkarsh Goel <utkarsh@deploif.ai>, Sean Chok <seanchok@deploif.ai>
Requires-Python: >=3.7
